five9/__init__.py
five9/environment.py
five9/exceptions.py
five9/five9.py
five9/models/__init__.py
five9/models/base_model.py
five9/models/disposition.py
five9/models/disposition_type_params.py
five9/models/key_value_pair.py
five9/models/timer.py
five9/models/web_connector.py
five9/tests/__init__.py
five9/tests/common.py
five9/tests/common_crud.py
five9/tests/test_api.py
five9/tests/test_base_model.py
five9/tests/test_disposition.py
five9/tests/test_environment.py
five9/tests/test_five9.py
five9/tests/test_key_value_pair.py
five9/tests/test_web_connector.py
five9-0.0.3b192.dist-info/DESCRIPTION.rst
five9-0.0.3b192.dist-info/METADATA
five9-0.0.3b192.dist-info/RECORD
five9-0.0.3b192.dist-info/WHEEL
five9-0.0.3b192.dist-info/metadata.json
five9-0.0.3b192.dist-info/top_level.txt
