Metadata-Version: 2.0
Name: five9
Version: 0.0.3b192
Summary: This library allows for you to integrate with Five9 Cloud Contact Center using Python.
Home-page: https://laslabs.github.io/python-five9
Author: LasLabs Inc.
Author-email: support@laslabs.com
License: MIT
Download-URL: https://github.com/LasLabs/python-five9
Platform: UNKNOWN
Classifier: Development Status :: 4 - Beta
Classifier: Environment :: Console
Classifier: Intended Audience :: Developers
Classifier: License :: OSI Approved :: MIT License
Classifier: Programming Language :: Python
Classifier: Programming Language :: Python :: 2
Classifier: Programming Language :: Python :: 2.7
Classifier: Programming Language :: Python :: 3
Classifier: Programming Language :: Python :: 3.4
Classifier: Programming Language :: Python :: 3.5
Classifier: Programming Language :: Python :: 3.6
Classifier: Topic :: Software Development :: Libraries :: Python Modules
Requires-Dist: properties
Requires-Dist: requests
Requires-Dist: six
Requires-Dist: websocket-client
Requires-Dist: zeep
